LICENSE.txt
MANIFEST.in
README.md
setup.py
NimingCypher/BaseConverter.py
NimingCypher/Chiffrement.py
NimingCypher/Exchange.py
NimingCypher/GetWebText.py
NimingCypher/Niming.py
NimingCypher/__init__.py
NimingCypher.egg-info/PKG-INFO
NimingCypher.egg-info/SOURCES.txt
NimingCypher.egg-info/dependency_links.txt
NimingCypher.egg-info/requires.txt
NimingCypher.egg-info/top_level.txt