Metadata-Version: 2.1
Name: NimingCypher
Version: 2.6.3
Summary: Encryption module for instant messaging
Home-page: UNKNOWN
Author: Arnaud Gissinger
License: CC ANCSA 4.0
Keywords: encryption module instant messaging free
Platform: UNKNOWN
Classifier: Development Status :: 5 - Production/Stable
Classifier: Intended Audience :: Developers
Classifier: Intended Audience :: Education
Classifier: Topic :: Security :: Cryptography
Classifier: License :: Free for non-commercial use
Classifier: Programming Language :: Python :: 3
